keyname/__init__.py
keyname/cli.py
keyname/keyname.py
keyname/version.py
keyname-0.6.0.dist-info/AUTHORS.rst
keyname-0.6.0.dist-info/LICENSE
keyname-0.6.0.dist-info/METADATA
keyname-0.6.0.dist-info/WHEEL
keyname-0.6.0.dist-info/entry_points.txt
keyname-0.6.0.dist-info/top_level.txt
keyname-0.6.0.dist-info/RECORD
