Metadata-Version: 2.1
Name: keyname
Version: 0.6.0
Summary: Easily pack and unpack metadata in a filename.
Home-page: https://github.com/mmore500/keyname
Author: Matthew Andres Moreno
Author-email: m.more500@gmail.com
License: MIT license
Keywords: keyname
Classifier: Development Status :: 2 - Pre-Alpha
Classifier: Intended Audience :: Developers
Classifier: License :: OSI Approved :: MIT License
Classifier: Natural Language :: English
Classifier: Programming Language :: Python :: 3
Classifier: Programming Language :: Python :: 3.6
Classifier: Programming Language :: Python :: 3.7
Classifier: Programming Language :: Python :: 3.8
Classifier: Programming Language :: Python :: 3.9
Classifier: Programming Language :: Python :: 3.10
Classifier: Programming Language :: Python :: 3.11
License-File: LICENSE
License-File: AUTHORS.rst
Requires-Dist: Click (>=6.0)
Requires-Dist: more-itertools (>=8.14.0)
Requires-Dist: retry (>=0.9.2)
